timberjack/__init__.py
timberjack/compat.py
timberjack/configure.py
timberjack/events.py
timberjack/middleware.py
timberjack/processors.py
timberjack/utils.py
timberjack/contrib/__init__.py
timberjack/contrib/flask.py
timberjack-0.1.0.dist-info/DESCRIPTION.rst
timberjack-0.1.0.dist-info/METADATA
timberjack-0.1.0.dist-info/RECORD
timberjack-0.1.0.dist-info/WHEEL
timberjack-0.1.0.dist-info/metadata.json
timberjack-0.1.0.dist-info/top_level.txt
