Metadata-Version: 2.0
Name: timberjack
Version: 0.1.0
Summary: Logging toolbox for Python services at Mobify.
Home-page: https://timberjack.readthedocs.org
Author: Sebastian Vetter
Author-email: seb@mobify.com
License: MIT
Platform: UNKNOWN
Classifier: Development Status :: 1 - Planning
Classifier: License :: OSI Approved :: MIT License
Classifier: Intended Audience :: Developers
Classifier: Programming Language :: Python
Classifier: Programming Language :: Python :: 2
Classifier: Programming Language :: Python :: 2.7
Classifier: Programming Language :: Python :: 3
Classifier: Programming Language :: Python :: 3.3
Classifier: Programming Language :: Python :: 3.4
Classifier: Programming Language :: Python :: 3.5
Classifier: Programming Language :: Python :: Implementation :: CPython
Requires-Dist: structlog
Provides-Extra: dev
Requires-Dist: bumpversion; extra == 'dev'
Requires-Dist: django; extra == 'dev'
Requires-Dist: flask; extra == 'dev'
Requires-Dist: pytest; extra == 'dev'
Requires-Dist: pytest-cache; extra == 'dev'
Requires-Dist: pytest-cov; extra == 'dev'
Requires-Dist: pytest-django; extra == 'dev'
Requires-Dist: rstcheck; extra == 'dev'
Requires-Dist: twine; extra == 'dev'
Provides-Extra: test
Requires-Dist: django; extra == 'test'
Requires-Dist: flask; extra == 'test'
Requires-Dist: pytest; extra == 'test'
Requires-Dist: pytest-cache; extra == 'test'
Requires-Dist: pytest-cov; extra == 'test'
Requires-Dist: pytest-django; extra == 'test'
Requires-Dist: rstcheck; extra == 'test'
